databuilder/__init__.py
databuilder/databuilder.py
databuilder/fields/__init__.py
databuilder/fields/fields.py
databuilder/options/__init__.py
databuilder/options/options.py
test/__init__.py
test/test_stuff.py
tests/__init__.py
tests/test_stuff.py
databuilder-0.0.2.dist-info/METADATA
databuilder-0.0.2.dist-info/WHEEL
databuilder-0.0.2.dist-info/top_level.txt
databuilder-0.0.2.dist-info/RECORD
