Metadata-Version: 2.1
Name: databuilder
Version: 0.0.2
Summary: a tool for quickly generating dummy data
Home-page: https://github.com/dbusteed/databuilder
Author: Davis Busteed
Author-email: busteed.davis@gmail.com
License: MIT
Platform: UNKNOWN
Classifier: License :: OSI Approved :: MIT License
Classifier: Programming Language :: Python :: 3
Requires-Dist: pandas (~=1.0.5)
Requires-Dist: numpy (~=1.19.1)
Requires-Dist: names (~=0.3.0)
Requires-Dist: brule (~=0.2.0)
